scipy-stubs/sparse/__init__.pyi
scipy-stubs/sparse/_base.pyi
scipy-stubs/sparse/_bsr.pyi
scipy-stubs/sparse/_construct.pyi
scipy-stubs/sparse/_coo.pyi
scipy-stubs/sparse/_csc.pyi
scipy-stubs/sparse/_csr.pyi
scipy-stubs/sparse/_data.pyi
scipy-stubs/sparse/_dia.pyi
scipy-stubs/sparse/_dok.pyi
scipy-stubs/sparse/_extract.pyi
scipy-stubs/sparse/_index.pyi
scipy-stubs/sparse/_lil.pyi
scipy-stubs/sparse/_matrix.pyi
scipy-stubs/sparse/_matrix_io.pyi
scipy-stubs/sparse/_sparsetools.pyi
scipy-stubs/sparse/_sputils.pyi
scipy-stubs/sparse/base.pyi
scipy-stubs/sparse/bsr.pyi
scipy-stubs/sparse/compressed.pyi
scipy-stubs/sparse/construct.pyi
scipy-stubs/sparse/coo.pyi
scipy-stubs/sparse/csc.pyi
scipy-stubs/sparse/csr.pyi
scipy-stubs/sparse/data.pyi
scipy-stubs/sparse/dia.pyi
scipy-stubs/sparse/dok.pyi
scipy-stubs/sparse/extract.pyi
scipy-stubs/sparse/lil.pyi
scipy-stubs/sparse/py.typed
scipy-stubs/sparse/sparsetools.pyi
scipy-stubs/sparse/spfuncs.pyi
scipy-stubs/sparse/sputils.pyi
scipy-stubs/sparse/typing.pyi
scipy-stubs/sparse/csgraph/__init__.pyi
scipy-stubs/sparse/linalg/__init__.pyi
types_scipy_sparse-0.1.0.dist-info/METADATA
types_scipy_sparse-0.1.0.dist-info/WHEEL
types_scipy_sparse-0.1.0.dist-info/licenses/LICENSE
types_scipy_sparse-0.1.0.dist-info/RECORD
