Metadata-Version: 2.3
Name: types-scipy-sparse
Version: 0.1.0
Summary: Type hints for scipy sparse module
Project-URL: homepage, https://github.com/BarakKatzir/types-scipy-sparse
Project-URL: Repository, https://github.com/BarakKatzir/types-scipy-sparse
Project-URL: source, https://github.com/BarakKatzir/types-scipy-sparse
Project-URL: download, https://github.com/BarakKatzir/types-scipy-sparse/releases
Project-URL: tracker, https://github.com/BarakKatzir/types-scipy-sparse/issues
Author-email: "Barak A. Katzir" <barakatzir@gmail.com>
License: BSD 3-Clause License
License-File: LICENSE
Keywords: scipy,sparse,stubs,type hint
Classifier: Intended Audience :: Developers
Classifier: Intended Audience :: Science/Research
Classifier: License :: OSI Approved :: BSD License
Classifier: Programming Language :: Python
Classifier: Programming Language :: Python :: 3 :: Only
Classifier: Programming Language :: Python :: 3.10
Classifier: Programming Language :: Python :: 3.11
Classifier: Programming Language :: Python :: 3.12
Classifier: Topic :: Scientific/Engineering
Classifier: Topic :: Software Development :: Libraries
Classifier: Typing :: Stubs Only
Requires-Python: >=3.10
Requires-Dist: numpy<2,>=1.23.5
Requires-Dist: scipy>=1.14.0
Requires-Dist: typing-extensions>=4.12
